sunimage2stl/__init__.py
sunimage2stl/imageFinder.py
sunimage2stl/imagePlot.py
sunimage2stl/makeMovie.py
sunimage2stl/threeDplot.py
sunimage2stl-0.1.0.dist-info/METADATA
sunimage2stl-0.1.0.dist-info/RECORD
sunimage2stl-0.1.0.dist-info/WHEEL
sunimage2stl-0.1.0.dist-info/top_level.txt
