Metadata-Version: 2.1
Name: sunimage2stl
Version: 0.1.0
Summary: A module for creating solar stl files
Home-page: https://github.com/nathanielcrosby/sunimage2stl
Author: Nathaniel Crosby
Author-email: nathanielcrosby@verizon.net
License: UNKNOWN
Platform: UNKNOWN
Classifier: Development Status :: 3 - Alpha
Classifier: Intended Audience :: Developers
Classifier: Topic :: Software Development :: Build Tools
Classifier: Operating System :: OS Independent
Classifier: License :: OSI Approved :: MIT License
Classifier: Programming Language :: Python :: 2
Classifier: Programming Language :: Python :: 2.7
